README
setup.py
bingo_autotopic/__init__.py
bingo_autotopic/admin.py
bingo_autotopic/models.py
django_bingo_autotopic.egg-info/PKG-INFO
django_bingo_autotopic.egg-info/SOURCES.txt
django_bingo_autotopic.egg-info/dependency_links.txt
django_bingo_autotopic.egg-info/requires.txt
django_bingo_autotopic.egg-info/top_level.txt